LICENSE
MANIFEST.in
README.rst
requirements.dev.txt
requirements.txt
setup.py
test/test_runner.py
test/test_toplevel.py
test/test_tree.py
test/test_utils.py
xmlpumpkin/__init__.py
xmlpumpkin/runner.py
xmlpumpkin/tree.py
xmlpumpkin/utils.py
xmlpumpkin.egg-info/PKG-INFO
xmlpumpkin.egg-info/SOURCES.txt
xmlpumpkin.egg-info/dependency_links.txt
xmlpumpkin.egg-info/requires.txt
xmlpumpkin.egg-info/top_level.txt