Metadata-Version: 1.1
Name: xmlpumpkin
Version: 0.1
Summary: CaboCha output-XML accessor
Home-page: https://github.com/drowse314-dev-ymat/xmlpumpkin
Author: ymat
Author-email: drowse314@gmail.com
License: BSD
Keywords: cabocha nlp xml parsing
Platform: any
Classifier: Development Status :: 3 - Alpha
Classifier: Intended Audience :: Developers
Classifier: License :: OSI Approved :: BSD License
Classifier: Operating System :: OS Independent
Classifier: Programming Language :: Python :: 2.7
Classifier: Programming Language :: Python :: 3
Classifier: Topic :: Software Development :: Libraries
Classifier: Topic :: Utilities
